fulmar/EPIC2K2.json
fulmar/K22EPIC.json
fulmar/KIC2Kepler.json
fulmar/Kepler2KIC.json
fulmar/TIC2TOI.json
fulmar/TOI2TIC.json
fulmar/__init__.py
fulmar/estimators.py
fulmar/fulmar_constants.py
fulmar/func.py
fulmar/k2_cat.csv
fulmar/kepler_cat.csv
fulmar/main.py
fulmar/mission_dic_manager.py
fulmar/query.py
fulmar/tess_cat.csv
fulmar/time.py
fulmar/utils.py
fulmar/version.py
fulmar_astro-0.1.9.dist-info/LICENSE
fulmar_astro-0.1.9.dist-info/METADATA
fulmar_astro-0.1.9.dist-info/WHEEL
fulmar_astro-0.1.9.dist-info/top_level.txt
fulmar_astro-0.1.9.dist-info/RECORD
