Metadata-Version: 2.1
Name: fulmar-astro
Version: 0.1.9
Summary: Follow-Up Lightcurves Multitool Assisting Radial velocities
Home-page: https://github.com/astrojose9/fulmar
Author: José Rodrigues
Author-email: jose.rodrigues@astro.up.pt
License: MIT
Platform: UNKNOWN
Classifier: Intended Audience :: Science/Research
Classifier: Topic :: Scientific/Engineering :: Astronomy
Classifier: Development Status :: 5 - Production/Stable
Classifier: License :: OSI Approved :: MIT License
Classifier: Programming Language :: Python
Requires-Dist: arviz
Requires-Dist: astropy
Requires-Dist: celerite2
Requires-Dist: corner
Requires-Dist: exoplanet
Requires-Dist: lightkurve (>=2)
Requires-Dist: matplotlib
Requires-Dist: numpy (<1.21,>=1.17)
Requires-Dist: pymc3
Requires-Dist: pymc3-ext
Requires-Dist: transitleastsquares (>=1.0.31)
